synthetica/__init__.py
synthetica/settings.py
synthetica-0.0.1.dist-info/METADATA
synthetica-0.0.1.dist-info/RECORD
synthetica-0.0.1.dist-info/WHEEL
synthetica-0.0.1.dist-info/top_level.txt
