Metadata-Version: 2.1
Name: synthetica
Version: 0.0.1
Summary: A client for synthetica
Home-page: https://github.com/synthetica-bio/synthetica
Author: Synthetica Dev Team
Author-email: dev@mail.synthetica.bio
License: UNKNOWN
Platform: UNKNOWN
Classifier: Programming Language :: Python :: 3
Classifier: License :: OSI Approved :: MIT License
Classifier: Operating System :: OS Independent
